pycounts_kw/__init__.py
pycounts_kw/plotting.py
pycounts_kw/pycounts_kw.py
pycounts_kw-0.1.0.dist-info/LICENSE
pycounts_kw-0.1.0.dist-info/WHEEL
pycounts_kw-0.1.0.dist-info/METADATA
pycounts_kw-0.1.0.dist-info/RECORD
