Metadata-Version: 2.1
Name: pycounts-kw
Version: 0.1.0
Summary: python package for text loading, cleaning and word counting
License: MIT
Author: kellywujy
Requires-Python: >=3.9,<4.0
Classifier: License :: OSI Approved :: MIT License
Classifier: Programming Language :: Python :: 3
Classifier: Programming Language :: Python :: 3.9
Classifier: Programming Language :: Python :: 3.10
Classifier: Programming Language :: Python :: 3.11
Requires-Dist: matplotlib (>=3.6.2,<4.0.0)
